imjoy_utils/VERSION
imjoy_utils/__init__.py
imjoy_utils-0.1.2.dist-info/LICENSE
imjoy_utils-0.1.2.dist-info/METADATA
imjoy_utils-0.1.2.dist-info/WHEEL
imjoy_utils-0.1.2.dist-info/top_level.txt
imjoy_utils-0.1.2.dist-info/RECORD
