Metadata-Version: 2.1
Name: imjoy-utils
Version: 0.1.2
Summary: Utility functions for ImJoy
Home-page: https://github.com/imjoy-team/imjoy-utils
Author: ImJoy-Team
Author-email: imjoy.team@gmail.com
License: MIT
Platform: UNKNOWN
Classifier: Development Status :: 3 - Alpha
Classifier: Environment :: Web Environment
Classifier: Intended Audience :: Developers
Classifier: License :: OSI Approved :: MIT License
Classifier: Operating System :: OS Independent
Classifier: Programming Language :: Python
Classifier: Programming Language :: Python :: 3.7
Classifier: Programming Language :: Python :: 3.8
Classifier: Programming Language :: Python :: 3.9
Classifier: Programming Language :: Python :: 3.10
Classifier: Topic :: Internet
Requires-Python: >=3.7
License-File: LICENSE
